laion_clap/__init__.py
laion_clap/hook.py
laion_clap/unit_test.py
laion_clap/clap_module/__init__.py
laion_clap/clap_module/bert.py
laion_clap/clap_module/bpe_simple_vocab_16e6.txt.gz
laion_clap/clap_module/factory.py
laion_clap/clap_module/feature_fusion.py
laion_clap/clap_module/htsat.py
laion_clap/clap_module/linear_probe.py
laion_clap/clap_module/loss.py
laion_clap/clap_module/model.py
laion_clap/clap_module/openai.py
laion_clap/clap_module/pann_model.py
laion_clap/clap_module/pretrained.py
laion_clap/clap_module/timm_model.py
laion_clap/clap_module/tokenizer.py
laion_clap/clap_module/transform.py
laion_clap/clap_module/utils.py
laion_clap/clap_module/version.py
laion_clap/clap_module/model_configs/HTSAT-base.json
laion_clap/clap_module/model_configs/HTSAT-large.json
laion_clap/clap_module/model_configs/HTSAT-tiny-win-1536.json
laion_clap/clap_module/model_configs/HTSAT-tiny.json
laion_clap/clap_module/model_configs/PANN-10.json
laion_clap/clap_module/model_configs/PANN-14-fmax-18k.json
laion_clap/clap_module/model_configs/PANN-14-fmax-8k-20s.json
laion_clap/clap_module/model_configs/PANN-14-tiny-transformer.json
laion_clap/clap_module/model_configs/PANN-14-win-1536.json
laion_clap/clap_module/model_configs/PANN-14.json
laion_clap/clap_module/model_configs/PANN-6.json
laion_clap/clap_module/model_configs/RN101-quickgelu.json
laion_clap/clap_module/model_configs/RN101.json
laion_clap/clap_module/model_configs/RN50-quickgelu.json
laion_clap/clap_module/model_configs/RN50.json
laion_clap/clap_module/model_configs/RN50x16.json
laion_clap/clap_module/model_configs/RN50x4.json
laion_clap/clap_module/model_configs/ViT-B-16.json
laion_clap/clap_module/model_configs/ViT-B-32-quickgelu.json
laion_clap/clap_module/model_configs/ViT-B-32.json
laion_clap/clap_module/model_configs/ViT-L-14.json
laion_clap/evaluate/__init__.py
laion_clap/evaluate/eval_dcase.py
laion_clap/evaluate/eval_linear_probe.py
laion_clap/evaluate/eval_retrieval.py
laion_clap-1.1.6.dist-info/LICENSE
laion_clap-1.1.6.dist-info/METADATA
laion_clap-1.1.6.dist-info/WHEEL
laion_clap-1.1.6.dist-info/top_level.txt
laion_clap-1.1.6.dist-info/RECORD
