Metadata-Version: 2.1
Name: laion_clap
Version: 1.1.6
Summary: Contrastive Language-Audio Pretraining Model from LAION
Author: Yusong Wu, Tianyu Zhang, Yuchen Hui
Author-email: Ke Chen <knutchen@ucsd.edu>
Maintainer: Yusong Wu, Tianyu Zhang, Yuchen Hui
Maintainer-email: Ke Chen <knutchen@ucsd.edu>
License: Creative Commons Legal Code
Project-URL: Homepage, https://github.com/LAION-AI/CLAP
Project-URL: Bug Tracker, https://github.com/LAION-AI/CLAP/issues
Classifier: Development Status :: 3 - Alpha
Classifier: Intended Audience :: Developers
Classifier: Intended Audience :: Science/Research
Classifier: License :: OSI Approved :: Apache Software License
Classifier: Topic :: Scientific/Engineering :: Artificial Intelligence
Requires-Python: >=3.7
License-File: LICENSE
Requires-Dist: numpy ==1.23.5
Requires-Dist: soundfile
Requires-Dist: librosa
Requires-Dist: torchlibrosa
Requires-Dist: ftfy
Requires-Dist: braceexpand
Requires-Dist: webdataset
Requires-Dist: wget
Requires-Dist: wandb
Requires-Dist: llvmlite
Requires-Dist: scipy
Requires-Dist: scikit-learn
Requires-Dist: pandas
Requires-Dist: h5py
Requires-Dist: tqdm
Requires-Dist: regex
Requires-Dist: transformers
Requires-Dist: progressbar
